aioia_core/__init__.py
aioia_core/auth.py
aioia_core/errors/__init__.py
aioia_core/errors/error_codes.py
aioia_core/errors/error_responses.py
aioia_core/factories/__init__.py
aioia_core/factories/base_manager_factory.py
aioia_core/factories/base_repository_factory.py
aioia_core/fastapi/__init__.py
aioia_core/fastapi/base_crud_router.py
aioia_core/managers.py
aioia_core/models.py
aioia_core/py.typed
aioia_core/repositories.py
aioia_core/settings.py
aioia_core/testing/__init__.py
aioia_core/testing/crud_fixtures.py
aioia_core/testing/database_manager.py
aioia_core/types.py
aioia_core-2.3.0.dist-info/METADATA
aioia_core-2.3.0.dist-info/WHEEL
aioia_core-2.3.0.dist-info/RECORD
