Metadata-Version: 2.4
Name: aioia-core
Version: 2.3.0
Summary: Core infrastructure for AIoIA projects
License: Apache-2.0
Keywords: aioia,infrastructure,database,fastapi
Author: AIoIA, Inc.
Author-email: devops@aioia.ai
Requires-Python: >=3.10,<3.13
Classifier: License :: OSI Approved :: Apache Software License
Classifier: Programming Language :: Python :: 3
Classifier: Programming Language :: Python :: 3.10
Classifier: Programming Language :: Python :: 3.11
Classifier: Programming Language :: Python :: 3.12
Requires-Dist: fastapi (>=0.115.0,<0.116.0)
Requires-Dist: pydantic (>=2.5.0,<3.0.0)
Requires-Dist: pydantic-settings (>=2.0.0,<3.0.0)
Requires-Dist: pyhumps (>=3.8.0,<4.0.0)
Requires-Dist: python-jose (>=3.3.0,<4.0.0)
Requires-Dist: sentry-sdk (>=2.0.0,<3.0.0)
Requires-Dist: sqlalchemy (>=2.0.0,<3.0.0)
